bgp_collector_ovh/__init__.py
bgp_collector_ovh/cli.py
bgp_collector_ovh/collector.py
bgp_collector_ovh/logging.conf
bgp_collector_ovh/models.py
bgp_collector_ovh/db_tools/__init__.py
bgp_collector_ovh/db_tools/db_queries.py
bgp_collector_ovh/db_tools/init_db.py
bgp_collector_ovh/scripts/__init__.py
bgp_collector_ovh/scripts/add_nexthop.py
bgp_collector_ovh/scripts/nexthop_config.yaml
bgp_collector_ovh/services/__init__.py
bgp_collector_ovh/services/postgres_worker.py
bgp_collector_ovh/services/timescale_worker.py
bgp_collector_ovh/tools/__init__.py
bgp_collector_ovh/tools/time_handler.py
bgp_collector_ovh-0.1.16.dist-info/LICENSE
bgp_collector_ovh-0.1.16.dist-info/METADATA
bgp_collector_ovh-0.1.16.dist-info/WHEEL
bgp_collector_ovh-0.1.16.dist-info/entry_points.txt
bgp_collector_ovh-0.1.16.dist-info/top_level.txt
bgp_collector_ovh-0.1.16.dist-info/RECORD
