Metadata-Version: 2.1
Name: bgp_collector_ovh
Version: 0.1.16
Summary: BGP update collector for ExaBGP
Author: Welfi Kharroubi
License: MIT
Classifier: Programming Language :: Python :: 3
Classifier: License :: OSI Approved :: MIT License
Classifier: Operating System :: POSIX :: Linux
Requires-Python: >=3.10
License-File: LICENSE
Requires-Dist: pika==1.3.2
Requires-Dist: psycopg2-binary==2.9.10
Requires-Dist: PyYAML==6.0.2
Requires-Dist: redis==5.2.1
Requires-Dist: SQLAlchemy==2.0.38
Requires-Dist: typing_extensions==4.12.2
Requires-Dist: click==8.1.7
